visual_guard/__init__.py
visual_guard/exceptions.py
visual_guard/logger.py
visual_guard/report.py
visual_guard/visual.py
visual_guard-0.2.1.dist-info/METADATA
visual_guard-0.2.1.dist-info/WHEEL
visual_guard-0.2.1.dist-info/top_level.txt
visual_guard-0.2.1.dist-info/RECORD
