Metadata-Version: 2.4
Name: visual-guard
Version: 0.2.1
Summary: A robust visual regression testing library for Python.
Home-page: https://github.com/godhiraj-code/visual-guard
Author: dhiraj
Author-email: dhiraj <dhirajdas.666@gmail.com>
License: MIT
Project-URL: Homepage, https://github.com/godhiraj-code/visual-guard
Classifier: Programming Language :: Python :: 3
Classifier: License :: OSI Approved :: MIT License
Classifier: Operating System :: OS Independent
Requires-Python: >=3.7
Requires-Dist: selenium>=4.0.0
Requires-Dist: Pillow>=9.0.0
Requires-Dist: colorama>=0.4.0
Requires-Dist: jinja2>=3.0.0
Requires-Dist: scikit-image>=0.19.0
Requires-Dist: numpy>=1.21.0
Requires-Dist: imagehash>=4.3.0
Dynamic: author
Dynamic: home-page
Dynamic: requires-python
